{
  "work": [
    {
      "@id": "_:b512iddOtlocdOtgovresourcesworks19077475",
      "@type": [
        "http://id.loc.gov/ontologies/bibframe/Topic",
        "http://www.loc.gov/mads/rdf/v1#ComplexSubject"
      ],
      "http://www.w3.org/2000/01/rdf-schema#label": [
        {
          "@value": "Vietnam War, 1961-1975--Personal narratives, Vietnamese--Comic books, strips, etc."
        }
      ],
      "http://www.loc.gov/mads/rdf/v1#authoritativeLabel": [
        {
          "@value": "Vietnam War, 1961-1975--Personal narratives, Vietnamese--Comic books, strips, etc."
        }
      ],
      "http://www.loc.gov/mads/rdf/v1#componentList": [
        {
          "@list": [
            {
              "@id": "_:b520iddOtlocdOtgovresourcesworks19077475"
            },
            {
              "@id": "_:b523iddOtlocdOtgovresourcesworks19077475"
            },
            {
              "@id": "_:b526iddOtlocdOtgovresourcesworks19077475"
            }
          ]
        }
      ],
      "http://id.loc.gov/ontologies/bflc/aap-normalized": [
        {
          "@value": "vietnamwar19611975personalnarrativesvietnamesecomicbooksstripsetc"
        }
      ],
      "http://www.loc.gov/mads/rdf/v1#isMemberOfMADSScheme": [
        {
          "@id": "http://id.loc.gov/vocabulary/subjectSchemes/sears"
        }
      ],
      "http://id.loc.gov/ontologies/bibframe/source": [
        {
          "@id": "http://id.loc.gov/vocabulary/subjectSchemes/sears"
        }
      ]
    },
    {
      "@id": "_:b526iddOtlocdOtgovresourcesworks19077475",
      "@type": [
        "http://www.loc.gov/mads/rdf/v1#GenreForm"
      ],
      "http://www.loc.gov/mads/rdf/v1#authoritativeLabel": [
        {
          "@value": "Comic books, strips, etc."
        }
      ]
    },
    {
      "@id": "_:b96iddOtlocdOtgovresourcesworks19077475",
      "@type": [
        "http://id.loc.gov/ontologies/bibframe/Classification"
      ],
      "http://id.loc.gov/ontologies/bibframe/classificationPortion": [
        {
          "@value": "SOC007000"
        }
      ],
      "http://id.loc.gov/ontologies/bibframe/source": [
        {
          "@id": "_:b100iddOtlocdOtgovresourcesworks19077475"
        }
      ]
    },
    {
      "@id": "_:b84iddOtlocdOtgovresourcesworks19077475",
      "@type": [
        "http://id.loc.gov/ontologies/bibframe/Source"
      ],
      "http://id.loc.gov/ontologies/bibframe/code": [
        {
          "@value": "bisacsh"
        }
      ]
    },
    {
      "@id": "http://id.loc.gov/vocabulary/relators/aut",
      "@type": [
        "http://id.loc.gov/ontologies/bibframe/Role"
      ],
      "http://www.w3.org/2000/01/rdf-schema#label": [
        {
          "@value": "Author"
        }
      ],
      "http://id.loc.gov/ontologies/bibframe/code": [
        {
          "@value": "aut"
        }
      ]
    },
    {
      "@id": "_:b331iddOtlocdOtgovresourcesworks19077475",
      "@type": [
        "http://www.loc.gov/mads/rdf/v1#Topic"
      ],
      "http://www.loc.gov/mads/rdf/v1#authoritativeLabel": [
        {
          "@value": "Vietnam War, 1961-1975"
        }
      ]
    },
    {
      "@id": "http://id.loc.gov/authorities/genreForms/gf2014026047",
      "@type": [
        "http://id.loc.gov/ontologies/bibframe/GenreForm"
      ],
      "http://www.w3.org/2000/01/rdf-schema#label": [
        {
          "@language": "en",
          "@value": "Autobiographies"
        }
      ],
      "http://id.loc.gov/ontologies/bflc/marcKey": [
        {
          "@value": "155  $aAutobiographies"
        }
      ]
    },
    {
      "@id": "http://id.loc.gov/authorities/genreForms/gf2014026229",
      "@type": [
        "http://id.loc.gov/ontologies/bibframe/GenreForm"
      ],
      "http://www.w3.org/2000/01/rdf-schema#label": [
        {
          "@language": "en",
          "@value": "Autobiographical comics"
        }
      ],
      "http://id.loc.gov/ontologies/bflc/marcKey": [
        {
          "@value": "155  $aAutobiographical comics"
        }
      ]
    },
    {
      "@id": "_:b459iddOtlocdOtgovresourcesworks19077475",
      "@type": [
        "http://www.loc.gov/mads/rdf/v1#Topic"
      ],
      "http://www.loc.gov/mads/rdf/v1#authoritativeLabel": [
        {
          "@value": "Vietnamese Americans"
        }
      ]
    },
    {
      "@id": "http://id.loc.gov/vocabulary/maudience/gen",
      "@type": [
        "http://id.loc.gov/ontologies/bibframe/IntendedAudience"
      ],
      "http://www.w3.org/2000/01/rdf-schema#label": [
        {
          "@value": "General"
        }
      ],
      "http://id.loc.gov/ontologies/bibframe/code": [
        {
          "@value": "gen"
        }
      ]
    },
    {
      "@id": "http://id.loc.gov/vocabulary/organizations/dlc",
      "@type": [
        "http://id.loc.gov/ontologies/bibframe/Organization",
        "http://id.loc.gov/ontologies/bibframe/Organization",
        "http://id.loc.gov/ontologies/bibframe/Organization"
      ],
      "http://www.w3.org/2000/01/rdf-schema#label": [
        {
          "@value": "United States, Library of Congress"
        },
        {
          "@value": "United States, Library of Congress"
        },
        {
          "@value": "United States, Library of Congress"
        }
      ],
      "http://id.loc.gov/ontologies/bibframe/code": [
        {
          "@type": "http://id.loc.gov/datatypes/orgs/code",
          "@value": "DLC"
        },
        {
          "@type": "http://id.loc.gov/datatypes/orgs/normalized",
          "@value": "dlc"
        },
        {
          "@type": "http://id.loc.gov/datatypes/orgs/iso15511",
          "@value": "US-dlc"
        },
        {
          "@type": "http://id.loc.gov/datatypes/orgs/code",
          "@value": "DLC"
        },
        {
          "@type": "http://id.loc.gov/datatypes/orgs/normalized",
          "@value": "dlc"
        },
        {
          "@type": "http://id.loc.gov/datatypes/orgs/iso15511",
          "@value": "US-dlc"
        },
        {
          "@type": "http://id.loc.gov/datatypes/orgs/code",
          "@value": "DLC"
        },
        {
          "@type": "http://id.loc.gov/datatypes/orgs/normalized",
          "@value": "dlc"
        },
        {
          "@type": "http://id.loc.gov/datatypes/orgs/iso15511",
          "@value": "US-dlc"
        }
      ]
    },
    {
      "@id": "_:b566iddOtlocdOtgovresourcesworks19077475",
      "@type": [
        "http://id.loc.gov/ontologies/bibframe/Agent"
      ],
      "http://id.loc.gov/ontologies/bibframe/code": [
        {
          "@value": "BTCTA"
        }
      ]
    },
    {
      "@id": "http://id.loc.gov/authorities/subjects/sh85143275",
      "@type": [
        "http://www.loc.gov/mads/rdf/v1#Topic"
      ],
      "http://www.w3.org/2000/01/rdf-schema#label": [
        {
          "@language": "en",
          "@value": "Vietnamese Americans"
        }
      ],
      "http://id.loc.gov/ontologies/bflc/marcKey": [
        {
          "@value": "150 0$aVietnamese Americans"
        }
      ]
    },
    {
      "@id": "_:b298iddOtlocdOtgovresourcesworks19077475",
      "@type": [
        "http://id.loc.gov/ontologies/bibframe/Topic",
        "http://www.loc.gov/mads/rdf/v1#Topic"
      ],
      "http://www.w3.org/2000/01/rdf-schema#label": [
        {
          "@value": "Graphic novels"
        }
      ],
      "http://www.loc.gov/mads/rdf/v1#authoritativeLabel": [
        {
          "@value": "Graphic novels"
        }
      ],
      "http://id.loc.gov/ontologies/bflc/aap-normalized": [
        {
          "@value": "graphicnovels"
        }
      ]
    },
    {
      "@id": "_:b523iddOtlocdOtgovresourcesworks19077475",
      "@type": [
        "http://www.loc.gov/mads/rdf/v1#Topic"
      ],
      "http://www.loc.gov/mads/rdf/v1#authoritativeLabel": [
        {
          "@value": "Personal narratives, Vietnamese"
        }
      ]
    },
    {
      "@id": "_:b590iddOtlocdOtgovresourcesworks19077475",
      "@type": [
        "http://id.loc.gov/ontologies/bibframe/AdminMetadata"
      ],
      "http://id.loc.gov/ontologies/bibframe/status": [
        {
          "@id": "http://id.loc.gov/vocabulary/mstatus/c"
        }
      ],
      "http://id.loc.gov/ontologies/bibframe/agent": [
        {
          "@id": "http://id.loc.gov/vocabulary/organizations/dlcmrc"
        }
      ],
      "http://id.loc.gov/ontologies/bibframe/generationProcess": [
        {
          "@id": "https://github.com/lcnetdev/marc2bibframe2/releases/tag/v2.7.0"
        }
      ],
      "http://id.loc.gov/ontologies/bibframe/date": [
        {
          "@type": "http://www.w3.org/2001/XMLSchema#dateTime",
          "@value": "2024-08-03T16:20:01.711247-04:00"
        }
      ]
    },
    {
      "@id": "_:b150iddOtlocdOtgovresourcesworks19077475",
      "@type": [
        "http://id.loc.gov/ontologies/bibframe/Summary"
      ],
      "http://www.w3.org/2000/01/rdf-schema#label": [
        {
          "@value": "The author describes her experiences as a young Vietnamese immigrant, highlighting her family's move from their war-torn home to the United States in graphic novel format"
        }
      ]
    },
    {
      "@id": "_:b423iddOtlocdOtgovresourcesworks19077475",
      "@type": [
        "http://id.loc.gov/ontologies/bibframe/Topic",
        "http://www.loc.gov/mads/rdf/v1#ComplexSubject"
      ],
      "http://www.loc.gov/mads/rdf/v1#authoritativeLabel": [
        {
          "@value": "Bui, Thi--Comic books, strips, etc."
        }
      ],
      "http://www.loc.gov/mads/rdf/v1#componentList": [
        {
          "@list": [
            {
              "@id": "http://id.loc.gov/rwo/agents/n2017009993"
            },
            {
              "@id": "_:b434iddOtlocdOtgovresourcesworks19077475"
            }
          ]
        }
      ],
      "http://id.loc.gov/ontologies/bflc/aap-normalized": [
        {
          "@value": "buithicomicbooksstripsetc"
        }
      ],
      "http://www.loc.gov/mads/rdf/v1#isMemberOfMADSScheme": [
        {
          "@id": "http://id.loc.gov/vocabulary/subjectSchemes/sears"
        }
      ],
      "http://id.loc.gov/ontologies/bibframe/source": [
        {
          "@id": "http://id.loc.gov/vocabulary/subjectSchemes/sears"
        }
      ]
    },
    {
      "@id": "_:b255iddOtlocdOtgovresourcesworks19077475",
      "@type": [
        "http://id.loc.gov/ontologies/bibframe/Topic",
        "http://www.loc.gov/mads/rdf/v1#ComplexSubject"
      ],
      "http://www.w3.org/2000/01/rdf-schema#label": [
        {
          "@value": "Vietnam War, 1961-1975--Personal narratives, Vietnamese--Comic books, strips, etc."
        }
      ],
      "http://www.loc.gov/mads/rdf/v1#authoritativeLabel": [
        {
          "@value": "Vietnam War, 1961-1975--Personal narratives, Vietnamese--Comic books, strips, etc."
        }
      ],
      "http://www.loc.gov/mads/rdf/v1#isMemberOfMADSScheme": [
        {
          "@id": "http://id.loc.gov/authorities/subjects"
        }
      ],
      "http://www.loc.gov/mads/rdf/v1#componentList": [
        {
          "@list": [
            {
              "@id": "http://id.loc.gov/authorities/subjects/sh85143277"
            },
            {
              "@id": "_:b272iddOtlocdOtgovresourcesworks19077475"
            },
            {
              "@id": "http://id.loc.gov/authorities/subjects/sh99001401"
            }
          ]
        }
      ],
      "http://id.loc.gov/ontologies/bflc/aap-normalized": [
        {
          "@value": "vietnamwar19611975personalnarrativesvietnamesecomicbooksstripsetc"
        }
      ],
      "http://id.loc.gov/ontologies/bibframe/source": [
        {
          "@id": "http://id.loc.gov/authorities/subjects"
        }
      ]
    },
    {
      "@id": "http://id.loc.gov/vocabulary/menclvl/f",
      "@type": [
        "http://id.loc.gov/ontologies/bflc/EncodingLevel"
      ],
      "http://www.w3.org/2000/01/rdf-schema#label": [
        {
          "@value": "full"
        }
      ],
      "http://id.loc.gov/ontologies/bibframe/code": [
        {
          "@value": "f"
        }
      ]
    },
    {
      "@id": "http://id.loc.gov/vocabulary/geographicAreas/n-us",
      "@type": [
        "http://id.loc.gov/ontologies/bibframe/GeographicCoverage"
      ],
      "http://www.w3.org/2000/01/rdf-schema#label": [
        {
          "@language": "en",
          "@value": "United States"
        }
      ],
      "http://id.loc.gov/ontologies/bibframe/code": [
        {
          "@type": "http://www.w3.org/2001/XMLSchema#string",
          "@value": "n-us"
        }
      ]
    },
    {
      "@id": "http://id.loc.gov/vocabulary/languages/eng",
      "@type": [
        "http://id.loc.gov/ontologies/bibframe/Language",
        "http://id.loc.gov/ontologies/bibframe/Language"
      ],
      "http://www.w3.org/2000/01/rdf-schema#label": [
        {
          "@language": "en",
          "@value": "English"
        },
        {
          "@language": "en",
          "@value": "English"
        }
      ],
      "http://id.loc.gov/ontologies/bibframe/code": [
        {
          "@type": "http://www.w3.org/2001/XMLSchema#string",
          "@value": "eng"
        },
        {
          "@type": "http://www.w3.org/2001/XMLSchema#string",
          "@value": "eng"
        }
      ]
    },
    {
      "@id": "_:b272iddOtlocdOtgovresourcesworks19077475",
      "@type": [
        "http://www.loc.gov/mads/rdf/v1#GenreForm"
      ],
      "http://www.loc.gov/mads/rdf/v1#authoritativeLabel": [
        {
          "@value": "Personal narratives, Vietnamese"
        }
      ]
    },
    {
      "@id": "http://id.loc.gov/resources/instances/19077475",
      "@type": [
        "http://id.loc.gov/ontologies/bibframe/Instance"
      ],
      "http://id.loc.gov/ontologies/bibframe/title": [
        {
          "@id": "_:b546iddOtlocdOtgovresourcesworks19077475"
        }
      ],
      "http://id.loc.gov/ontologies/bibframe/publicationStatement": [
        {
          "@value": "New York: Abrams ComicArts, 2017"
        }
      ]
    },
    {
      "@id": "http://id.loc.gov/authorities/childrensSubjects/sj2021050875",
      "@type": [
        "http://id.loc.gov/ontologies/bibframe/Topic"
      ],
      "http://www.w3.org/2000/01/rdf-schema#label": [
        {
          "@language": "en",
          "@value": "Vietnam War, 1961-1975"
        }
      ],
      "http://id.loc.gov/ontologies/bflc/marcKey": [
        {
          "@value": "150  $aVietnam War, 1961-1975"
        }
      ]
    },
    {
      "@id": "http://id.loc.gov/vocabulary/organizations/dlcmrc",
      "@type": [
        "http://id.loc.gov/ontologies/bibframe/Agent",
        "http://id.loc.gov/ontologies/bibframe/Organization"
      ],
      "http://www.w3.org/2000/01/rdf-schema#label": [
        {
          "@value": "United States, Library of Congress, Network Development and MARC Standards Office"
        }
      ],
      "http://id.loc.gov/ontologies/bibframe/code": [
        {
          "@type": "http://id.loc.gov/datatypes/orgs/code",
          "@value": "DLC-MRC"
        },
        {
          "@type": "http://id.loc.gov/datatypes/orgs/normalized",
          "@value": "dlcmrc"
        },
        {
          "@type": "http://id.loc.gov/datatypes/orgs/iso15511",
          "@value": "US-dlcmrc"
        }
      ]
    },
    {
      "@id": "_:b46iddOtlocdOtgovresourcesworks19077475",
      "@type": [
        "http://id.loc.gov/ontologies/bibframe/ClassificationLcc"
      ],
      "http://id.loc.gov/ontologies/bibframe/classificationPortion": [
        {
          "@value": "E184.V53"
        }
      ],
      "http://id.loc.gov/ontologies/bibframe/itemPortion": [
        {
          "@value": "B85 2017"
        }
      ],
      "http://id.loc.gov/ontologies/bibframe/assigner": [
        {
          "@id": "http://id.loc.gov/vocabulary/organizations/dlc"
        }
      ],
      "http://id.loc.gov/ontologies/bibframe/status": [
        {
          "@id": "http://id.loc.gov/vocabulary/mstatus/uba"
        }
      ]
    },
    {
      "@id": "http://id.loc.gov/vocabulary/descriptionConventions/isbd",
      "@type": [
        "http://id.loc.gov/ontologies/bibframe/DescriptionConventions"
      ],
      "http://www.w3.org/2000/01/rdf-schema#label": [
        {
          "@value": "ISBD: International standard bibliographic description"
        }
      ],
      "http://id.loc.gov/ontologies/bibframe/code": [
        {
          "@value": "isbd"
        }
      ]
    },
    {
      "@id": "http://id.loc.gov/authorities/genreForms/gf2014026362",
      "@type": [
        "http://id.loc.gov/ontologies/bibframe/GenreForm",
        "http://id.loc.gov/ontologies/bibframe/GenreForm"
      ],
      "http://www.w3.org/2000/01/rdf-schema#label": [
        {
          "@language": "en",
          "@value": "Graphic novels"
        },
        {
          "@language": "en",
          "@value": "Graphic novels"
        }
      ],
      "http://id.loc.gov/ontologies/bflc/marcKey": [
        {
          "@value": "155  $aGraphic novels"
        },
        {
          "@value": "155  $aGraphic novels"
        }
      ]
    },
    {
      "@id": "_:b627iddOtlocdOtgovresourcesworks19077475",
      "@type": [
        "http://id.loc.gov/ontologies/bibframe/Local"
      ],
      "http://www.w3.org/1999/02/22-rdf-syntax-ns#value": [
        {
          "@value": "19077475"
        }
      ],
      "http://id.loc.gov/ontologies/bibframe/assigner": [
        {
          "@id": "http://id.loc.gov/vocabulary/organizations/dlc"
        }
      ]
    },
    {
      "@id": "http://id.loc.gov/vocabulary/descriptionConventions/rda",
      "@type": [
        "http://id.loc.gov/ontologies/bibframe/DescriptionConventions"
      ],
      "http://www.w3.org/2000/01/rdf-schema#label": [
        {
          "@value": "Resource description and access"
        }
      ],
      "http://id.loc.gov/ontologies/bibframe/code": [
        {
          "@value": "rda"
        }
      ]
    },
    {
      "@id": "_:b88iddOtlocdOtgovresourcesworks19077475",
      "@type": [
        "http://id.loc.gov/ontologies/bibframe/Classification"
      ],
      "http://id.loc.gov/ontologies/bibframe/classificationPortion": [
        {
          "@value": "CGN007000"
        }
      ],
      "http://id.loc.gov/ontologies/bibframe/source": [
        {
          "@id": "_:b92iddOtlocdOtgovresourcesworks19077475"
        }
      ]
    },
    {
      "@id": "_:b434iddOtlocdOtgovresourcesworks19077475",
      "@type": [
        "http://www.loc.gov/mads/rdf/v1#GenreForm"
      ],
      "http://www.loc.gov/mads/rdf/v1#authoritativeLabel": [
        {
          "@value": "Comic books, strips, etc."
        }
      ]
    },
    {
      "@id": "http://id.loc.gov/vocabulary/mstatus/c",
      "@type": [
        "http://id.loc.gov/ontologies/bibframe/Status",
        "http://id.loc.gov/ontologies/bibframe/Status"
      ],
      "http://www.w3.org/2000/01/rdf-schema#label": [
        {
          "@value": "changed"
        },
        {
          "@value": "changed"
        }
      ],
      "http://id.loc.gov/ontologies/bibframe/code": [
        {
          "@value": "c"
        },
        {
          "@value": "c"
        }
      ]
    },
    {
      "@id": "_:b100iddOtlocdOtgovresourcesworks19077475",
      "@type": [
        "http://id.loc.gov/ontologies/bibframe/Source"
      ],
      "http://id.loc.gov/ontologies/bibframe/code": [
        {
          "@value": "bisacsh"
        }
      ]
    },
    {
      "@id": "http://id.loc.gov/vocabulary/contentTypes/txt",
      "@type": [
        "http://id.loc.gov/ontologies/bibframe/Content"
      ],
      "http://www.w3.org/2000/01/rdf-schema#label": [
        {
          "@value": "text"
        }
      ],
      "http://id.loc.gov/ontologies/bibframe/code": [
        {
          "@value": "txt"
        }
      ]
    },
    {
      "@id": "http://id.loc.gov/vocabulary/relators/art",
      "@type": [
        "http://id.loc.gov/ontologies/bibframe/Role"
      ],
      "http://www.w3.org/2000/01/rdf-schema#label": [
        {
          "@value": "Artist"
        }
      ],
      "http://id.loc.gov/ontologies/bibframe/code": [
        {
          "@value": "art"
        }
      ]
    },
    {
      "@id": "_:b126iddOtlocdOtgovresourcesworks19077475",
      "@type": [
        "http://id.loc.gov/ontologies/bibframe/Title"
      ],
      "http://id.loc.gov/ontologies/bibframe/mainTitle": [
        {
          "@value": "The best we could do"
        }
      ],
      "http://id.loc.gov/ontologies/bflc/nonSortNum": [
        {
          "@value": "4"
        }
      ]
    },
    {
      "@id": "http://id.loc.gov/resources/works/19077475",
      "@type": [
        "http://id.loc.gov/ontologies/bibframe/Work",
        "http://id.loc.gov/ontologies/bibframe/Text",
        "http://id.loc.gov/ontologies/bibframe/Monograph"
      ],
      "http://id.loc.gov/ontologies/bflc/aap": [
        {
          "@value": "Bui, Thi The best we could do"
        }
      ],
      "http://id.loc.gov/ontologies/bflc/aap-normalized": [
        {
          "@value": "buithithebestwecoulddo"
        }
      ],
      "http://id.loc.gov/ontologies/bibframe/language": [
        {
          "@id": "http://id.loc.gov/vocabulary/languages/eng"
        }
      ],
      "http://id.loc.gov/ontologies/bibframe/illustrativeContent": [
        {
          "@id": "http://id.loc.gov/vocabulary/millus/ill"
        }
      ],
      "http://id.loc.gov/ontologies/bibframe/intendedAudience": [
        {
          "@id": "http://id.loc.gov/vocabulary/maudience/gen"
        }
      ],
      "http://id.loc.gov/ontologies/bibframe/genreForm": [
        {
          "@id": "http://id.loc.gov/authorities/genreForms/gf2014026047"
        },
        {
          "@id": "http://id.loc.gov/authorities/genreForms/gf2014026362"
        },
        {
          "@id": "http://id.loc.gov/authorities/genreForms/gf2014026229"
        },
        {
          "@id": "http://id.loc.gov/authorities/genreForms/gf2014026362"
        }
      ],
      "http://id.loc.gov/ontologies/bibframe/geographicCoverage": [
        {
          "@id": "http://id.loc.gov/vocabulary/geographicAreas/n-us"
        },
        {
          "@id": "http://id.loc.gov/vocabulary/geographicAreas/a-vt"
        }
      ],
      "http://id.loc.gov/ontologies/bibframe/classification": [
        {
          "@id": "_:b46iddOtlocdOtgovresourcesworks19077475"
        },
        {
          "@id": "_:b68iddOtlocdOtgovresourcesworks19077475"
        },
        {
          "@id": "_:b80iddOtlocdOtgovresourcesworks19077475"
        },
        {
          "@id": "_:b88iddOtlocdOtgovresourcesworks19077475"
        },
        {
          "@id": "_:b96iddOtlocdOtgovresourcesworks19077475"
        }
      ],
      "http://id.loc.gov/ontologies/bibframe/contribution": [
        {
          "@id": "_:b104iddOtlocdOtgovresourcesworks19077475"
        }
      ],
      "http://id.loc.gov/ontologies/bibframe/title": [
        {
          "@id": "_:b126iddOtlocdOtgovresourcesworks19077475"
        }
      ],
      "http://id.loc.gov/ontologies/bibframe/content": [
        {
          "@id": "http://id.loc.gov/vocabulary/contentTypes/txt"
        },
        {
          "@id": "http://id.loc.gov/vocabulary/contentTypes/sti"
        }
      ],
      "http://id.loc.gov/ontologies/bibframe/summary": [
        {
          "@id": "_:b150iddOtlocdOtgovresourcesworks19077475"
        },
        {
          "@id": "_:b154iddOtlocdOtgovresourcesworks19077475"
        }
      ],
      "http://id.loc.gov/ontologies/bibframe/subject": [
        {
          "@id": "_:b158iddOtlocdOtgovresourcesworks19077475"
        },
        {
          "@id": "_:b184iddOtlocdOtgovresourcesworks19077475"
        },
        {
          "@id": "_:b217iddOtlocdOtgovresourcesworks19077475"
        },
        {
          "@id": "_:b255iddOtlocdOtgovresourcesworks19077475"
        },
        {
          "@id": "http://id.loc.gov/authorities/childrensSubjects/sj2020050016"
        },
        {
          "@id": "http://id.loc.gov/authorities/childrensSubjects/sj2021050875"
        },
        {
          "@id": "_:b298iddOtlocdOtgovresourcesworks19077475"
        },
        {
          "@id": "_:b307iddOtlocdOtgovresourcesworks19077475"
        },
        {
          "@id": "_:b323iddOtlocdOtgovresourcesworks19077475"
        },
        {
          "@id": "_:b339iddOtlocdOtgovresourcesworks19077475"
        },
        {
          "@id": "_:b348iddOtlocdOtgovresourcesworks19077475"
        },
        {
          "@id": "_:b369iddOtlocdOtgovresourcesworks19077475"
        },
        {
          "@id": "_:b390iddOtlocdOtgovresourcesworks19077475"
        },
        {
          "@id": "_:b423iddOtlocdOtgovresourcesworks19077475"
        },
        {
          "@id": "_:b451iddOtlocdOtgovresourcesworks19077475"
        },
        {
          "@id": "_:b479iddOtlocdOtgovresourcesworks19077475"
        },
        {
          "@id": "_:b512iddOtlocdOtgovresourcesworks19077475"
        }
      ],
      "http://purl.org/dc/terms/isPartOf": [
        {
          "@id": "http://id.loc.gov/resources/works"
        }
      ],
      "http://id.loc.gov/ontologies/bibframe/hasInstance": [
        {
          "@id": "http://id.loc.gov/resources/instances/19077475"
        }
      ],
      "http://id.loc.gov/ontologies/bibframe/adminMetadata": [
        {
          "@id": "_:b556iddOtlocdOtgovresourcesworks19077475"
        },
        {
          "@id": "_:b570iddOtlocdOtgovresourcesworks19077475"
        },
        {
          "@id": "_:b590iddOtlocdOtgovresourcesworks19077475"
        },
        {
          "@id": "_:b612iddOtlocdOtgovresourcesworks19077475"
        }
      ]
    },
    {
      "@id": "_:b334iddOtlocdOtgovresourcesworks19077475",
      "@type": [
        "http://www.loc.gov/mads/rdf/v1#Topic"
      ],
      "http://www.loc.gov/mads/rdf/v1#authoritativeLabel": [
        {
          "@value": "Personal narratives, Vietnamese"
        }
      ]
    },
    {
      "@id": "_:b348iddOtlocdOtgovresourcesworks19077475",
      "@type": [
        "http://id.loc.gov/ontologies/bibframe/Topic",
        "http://www.loc.gov/mads/rdf/v1#Topic"
      ],
      "http://www.w3.org/2000/01/rdf-schema#label": [
        {
          "@value": "BIOGRAPHY & AUTOBIOGRAPHY / Personal Memoirs"
        }
      ],
      "http://www.loc.gov/mads/rdf/v1#authoritativeLabel": [
        {
          "@value": "BIOGRAPHY & AUTOBIOGRAPHY / Personal Memoirs"
        }
      ],
      "http://id.loc.gov/ontologies/bflc/aap-normalized": [
        {
          "@value": "biography&autobiography/personalmemoirs"
        }
      ],
      "http://www.loc.gov/mads/rdf/v1#isMemberOfMADSScheme": [
        {
          "@id": "http://id.loc.gov/vocabulary/subjectSchemes/bisacsh"
        }
      ],
      "http://id.loc.gov/ontologies/bibframe/source": [
        {
          "@id": "http://id.loc.gov/vocabulary/subjectSchemes/bisacsh"
        }
      ]
    },
    {
      "@id": "http://id.loc.gov/rwo/agents/n78095330-781",
      "@type": [
        "http://www.loc.gov/mads/rdf/v1#Geographic",
        "http://www.loc.gov/mads/rdf/v1#Geographic"
      ],
      "http://www.w3.org/2000/01/rdf-schema#label": [
        {
          "@value": "United States"
        },
        {
          "@value": "United States"
        }
      ],
      "http://id.loc.gov/ontologies/bflc/marcKey": [
        {
          "@value": "181  $zUnited States"
        },
        {
          "@value": "181  $zUnited States"
        }
      ]
    },
    {
      "@id": "_:b154iddOtlocdOtgovresourcesworks19077475",
      "@type": [
        "http://id.loc.gov/ontologies/bibframe/Summary"
      ],
      "http://www.w3.org/2000/01/rdf-schema#label": [
        {
          "@value": "\"Exploring the anguish of immigration and the lasting effects that displacement has on a child and her family, Bui documents the story of her family's daring escape after the fall of South Vietnam in the 1970s, and the difficulties they faced building new lives for themselves\"--Publisher description"
        }
      ]
    },
    {
      "@id": "http://id.loc.gov/authorities/subjects",
      "@type": [
        "http://www.loc.gov/mads/rdf/v1#MADSScheme",
        "http://id.loc.gov/ontologies/bibframe/Source",
        "http://www.loc.gov/mads/rdf/v1#MADSScheme",
        "http://id.loc.gov/ontologies/bibframe/Source",
        "http://www.loc.gov/mads/rdf/v1#MADSScheme",
        "http://id.loc.gov/ontologies/bibframe/Source",
        "http://www.loc.gov/mads/rdf/v1#MADSScheme",
        "http://id.loc.gov/ontologies/bibframe/Source"
      ],
      "http://www.w3.org/2000/01/rdf-schema#label": [
        {
          "@language": "en",
          "@value": "Library of Congress Subject Headings"
        },
        {
          "@language": "en",
          "@value": "Library of Congress Subject Headings"
        },
        {
          "@language": "en",
          "@value": "Library of Congress Subject Headings"
        },
        {
          "@language": "en",
          "@value": "Library of Congress Subject Headings"
        },
        {
          "@language": "en",
          "@value": "Library of Congress Subject Headings"
        },
        {
          "@language": "en",
          "@value": "Library of Congress Subject Headings"
        },
        {
          "@language": "en",
          "@value": "Library of Congress Subject Headings"
        },
        {
          "@language": "en",
          "@value": "Library of Congress Subject Headings"
        }
      ]
    },
    {
      "@id": "http://id.loc.gov/vocabulary/mstatus/n",
      "@type": [
        "http://id.loc.gov/ontologies/bibframe/Status"
      ],
      "http://www.w3.org/2000/01/rdf-schema#label": [
        {
          "@value": "new"
        }
      ],
      "http://id.loc.gov/ontologies/bibframe/code": [
        {
          "@value": "n"
        }
      ]
    },
    {
      "@id": "_:b570iddOtlocdOtgovresourcesworks19077475",
      "@type": [
        "http://id.loc.gov/ontologies/bibframe/AdminMetadata"
      ],
      "http://id.loc.gov/ontologies/bibframe/status": [
        {
          "@id": "http://id.loc.gov/vocabulary/mstatus/c"
        }
      ],
      "http://id.loc.gov/ontologies/bibframe/date": [
        {
          "@type": "http://www.w3.org/2001/XMLSchema#dateTime",
          "@value": "2017-10-26T08:31:24"
        }
      ],
      "http://id.loc.gov/ontologies/bibframe/descriptionModifier": [
        {
          "@id": "http://id.loc.gov/vocabulary/organizations/dlc"
        }
      ]
    },
    {
      "@id": "http://id.loc.gov/authorities/subjects/sh85143277",
      "@type": [
        "http://www.loc.gov/mads/rdf/v1#Topic"
      ],
      "http://www.w3.org/2000/01/rdf-schema#label": [
        {
          "@language": "en",
          "@value": "Vietnam War, 1961-1975"
        }
      ],
      "http://id.loc.gov/ontologies/bflc/marcKey": [
        {
          "@value": "150  $aVietnam War, 1961-1975"
        }
      ]
    },
    {
      "@id": "http://id.loc.gov/vocabulary/mstatus/uba",
      "@type": [
        "http://id.loc.gov/ontologies/bibframe/Status"
      ],
      "http://www.w3.org/2000/01/rdf-schema#label": [
        {
          "@value": "used by assigner"
        }
      ],
      "http://id.loc.gov/ontologies/bibframe/code": [
        {
          "@value": "uba"
        }
      ]
    },
    {
      "@id": "_:b74iddOtlocdOtgovresourcesworks19077475",
      "@type": [
        "http://id.loc.gov/ontologies/bibframe/Source"
      ],
      "http://id.loc.gov/ontologies/bibframe/code": [
        {
          "@value": "23"
        }
      ]
    },
    {
      "@id": "http://id.loc.gov/vocabulary/millus/ill",
      "@type": [
        "http://id.loc.gov/ontologies/bibframe/Illustration"
      ],
      "http://www.w3.org/2000/01/rdf-schema#label": [
        {
          "@value": "Illustrations"
        }
      ],
      "http://id.loc.gov/ontologies/bibframe/code": [
        {
          "@value": "ill"
        }
      ]
    },
    {
      "@id": "_:b68iddOtlocdOtgovresourcesworks19077475",
      "@type": [
        "http://id.loc.gov/ontologies/bibframe/ClassificationDdc"
      ],
      "http://id.loc.gov/ontologies/bibframe/classificationPortion": [
        {
          "@value": "973/.0495920092"
        },
        {
          "@value": "B"
        }
      ],
      "http://id.loc.gov/ontologies/bibframe/source": [
        {
          "@id": "_:b74iddOtlocdOtgovresourcesworks19077475"
        }
      ],
      "http://id.loc.gov/ontologies/bibframe/edition": [
        {
          "@value": "full"
        }
      ]
    },
    {
      "@id": "http://id.loc.gov/authorities/subjects/sh99001401",
      "@type": [
        "http://www.loc.gov/mads/rdf/v1#GenreForm",
        "http://www.loc.gov/mads/rdf/v1#GenreForm",
        "http://www.loc.gov/mads/rdf/v1#GenreForm",
        "http://www.loc.gov/mads/rdf/v1#GenreForm"
      ],
      "http://www.w3.org/2000/01/rdf-schema#label": [
        {
          "@language": "en",
          "@value": "Comic books, strips, etc."
        },
        {
          "@language": "en",
          "@value": "Comic books, strips, etc."
        },
        {
          "@language": "en",
          "@value": "Comic books, strips, etc."
        },
        {
          "@language": "en",
          "@value": "Comic books, strips, etc."
        }
      ],
      "http://id.loc.gov/ontologies/bflc/marcKey": [
        {
          "@value": "185  $vComic books, strips, etc."
        },
        {
          "@value": "185  $vComic books, strips, etc."
        },
        {
          "@value": "185  $vComic books, strips, etc."
        },
        {
          "@value": "185  $vComic books, strips, etc."
        }
      ]
    },
    {
      "@id": "_:b495iddOtlocdOtgovresourcesworks19077475",
      "@type": [
        "http://www.loc.gov/mads/rdf/v1#GenreForm"
      ],
      "http://www.loc.gov/mads/rdf/v1#authoritativeLabel": [
        {
          "@value": "Comic books, strips, etc."
        }
      ]
    },
    {
      "@id": "_:b339iddOtlocdOtgovresourcesworks19077475",
      "@type": [
        "http://id.loc.gov/ontologies/bibframe/Topic",
        "http://www.loc.gov/mads/rdf/v1#Topic"
      ],
      "http://www.w3.org/2000/01/rdf-schema#label": [
        {
          "@value": "Vietnamese Americans"
        }
      ],
      "http://www.loc.gov/mads/rdf/v1#authoritativeLabel": [
        {
          "@value": "Vietnamese Americans"
        }
      ],
      "http://id.loc.gov/ontologies/bflc/aap-normalized": [
        {
          "@value": "vietnameseamericans"
        }
      ]
    },
    {
      "@id": "_:b104iddOtlocdOtgovresourcesworks19077475",
      "@type": [
        "http://id.loc.gov/ontologies/bibframe/Contribution",
        "http://id.loc.gov/ontologies/bibframe/PrimaryContribution"
      ],
      "http://id.loc.gov/ontologies/bibframe/agent": [
        {
          "@id": "http://id.loc.gov/rwo/agents/n2017009993"
        }
      ],
      "http://id.loc.gov/ontologies/bibframe/role": [
        {
          "@id": "http://id.loc.gov/vocabulary/relators/aut"
        },
        {
          "@id": "http://id.loc.gov/vocabulary/relators/art"
        }
      ]
    },
    {
      "@id": "_:b556iddOtlocdOtgovresourcesworks19077475",
      "@type": [
        "http://id.loc.gov/ontologies/bibframe/AdminMetadata"
      ],
      "http://id.loc.gov/ontologies/bibframe/status": [
        {
          "@id": "http://id.loc.gov/vocabulary/mstatus/n"
        }
      ],
      "http://id.loc.gov/ontologies/bibframe/date": [
        {
          "@type": "http://www.w3.org/2001/XMLSchema#date",
          "@value": "2016-04-28"
        }
      ],
      "http://id.loc.gov/ontologies/bibframe/agent": [
        {
          "@id": "_:b566iddOtlocdOtgovresourcesworks19077475"
        }
      ]
    },
    {
      "@id": "http://id.loc.gov/authorities/subjects/sh85112299",
      "@type": [
        "http://www.loc.gov/mads/rdf/v1#Topic"
      ],
      "http://www.w3.org/2000/01/rdf-schema#label": [
        {
          "@language": "en",
          "@value": "Refugees"
        }
      ],
      "http://id.loc.gov/ontologies/bflc/marcKey": [
        {
          "@value": "150  $aRefugees"
        }
      ]
    },
    {
      "@id": "http://id.loc.gov/vocabulary/contentTypes/sti",
      "@type": [
        "http://id.loc.gov/ontologies/bibframe/Content"
      ],
      "http://www.w3.org/2000/01/rdf-schema#label": [
        {
          "@value": "still image"
        }
      ],
      "http://id.loc.gov/ontologies/bibframe/code": [
        {
          "@value": "sti"
        }
      ]
    },
    {
      "@id": "http://id.loc.gov/authorities/subjects/sh99001237",
      "@type": [
        "http://www.loc.gov/mads/rdf/v1#GenreForm",
        "http://www.loc.gov/mads/rdf/v1#GenreForm"
      ],
      "http://www.w3.org/2000/01/rdf-schema#label": [
        {
          "@language": "en",
          "@value": "Biography"
        },
        {
          "@language": "en",
          "@value": "Biography"
        }
      ],
      "http://id.loc.gov/ontologies/bflc/marcKey": [
        {
          "@value": "185  $vBiography"
        },
        {
          "@value": "185  $vBiography"
        }
      ]
    },
    {
      "@id": "_:b184iddOtlocdOtgovresourcesworks19077475",
      "@type": [
        "http://id.loc.gov/ontologies/bibframe/Topic",
        "http://www.loc.gov/mads/rdf/v1#ComplexSubject"
      ],
      "http://www.w3.org/2000/01/rdf-schema#label": [
        {
          "@value": "Vietnamese Americans--Biography--Comic books, strips, etc."
        }
      ],
      "http://www.loc.gov/mads/rdf/v1#authoritativeLabel": [
        {
          "@value": "Vietnamese Americans--Biography--Comic books, strips, etc."
        }
      ],
      "http://www.loc.gov/mads/rdf/v1#isMemberOfMADSScheme": [
        {
          "@id": "http://id.loc.gov/authorities/subjects"
        }
      ],
      "http://www.loc.gov/mads/rdf/v1#componentList": [
        {
          "@list": [
            {
              "@id": "http://id.loc.gov/authorities/subjects/sh85143275"
            },
            {
              "@id": "http://id.loc.gov/authorities/subjects/sh99001237"
            },
            {
              "@id": "http://id.loc.gov/authorities/subjects/sh99001401"
            }
          ]
        }
      ],
      "http://id.loc.gov/ontologies/bflc/aap-normalized": [
        {
          "@value": "vietnameseamericansbiographycomicbooksstripsetc"
        }
      ],
      "http://id.loc.gov/ontologies/bibframe/source": [
        {
          "@id": "http://id.loc.gov/authorities/subjects"
        }
      ]
    },
    {
      "@id": "http://id.loc.gov/authorities/childrensSubjects/sj2020050016",
      "@type": [
        "http://id.loc.gov/ontologies/bibframe/subject"
      ],
      "http://www.w3.org/2000/01/rdf-schema#label": [
        {
          "@language": "en",
          "@value": "Cartoons and comics"
        }
      ],
      "http://id.loc.gov/ontologies/bflc/marcKey": [
        {
          "@value": "185  $vCartoons and comics"
        }
      ]
    },
    {
      "@id": "http://id.loc.gov/vocabulary/marcauthen/lccopycat",
      "@type": [
        "http://id.loc.gov/ontologies/bibframe/DescriptionAuthentication"
      ],
      "http://www.w3.org/2000/01/rdf-schema#label": [
        {
          "@value": "LC Copy Cataloging"
        }
      ],
      "http://id.loc.gov/ontologies/bibframe/code": [
        {
          "@value": "lccopycat"
        }
      ]
    },
    {
      "@id": "_:b323iddOtlocdOtgovresourcesworks19077475",
      "@type": [
        "http://id.loc.gov/ontologies/bibframe/Topic",
        "http://www.loc.gov/mads/rdf/v1#ComplexSubject"
      ],
      "http://www.w3.org/2000/01/rdf-schema#label": [
        {
          "@value": "Vietnam War, 1961-1975--Personal narratives, Vietnamese"
        }
      ],
      "http://www.loc.gov/mads/rdf/v1#authoritativeLabel": [
        {
          "@value": "Vietnam War, 1961-1975--Personal narratives, Vietnamese"
        }
      ],
      "http://www.loc.gov/mads/rdf/v1#componentList": [
        {
          "@list": [
            {
              "@id": "_:b331iddOtlocdOtgovresourcesworks19077475"
            },
            {
              "@id": "_:b334iddOtlocdOtgovresourcesworks19077475"
            }
          ]
        }
      ],
      "http://id.loc.gov/ontologies/bflc/aap-normalized": [
        {
          "@value": "vietnamwar19611975personalnarrativesvietnamese"
        }
      ]
    },
    {
      "@id": "_:b369iddOtlocdOtgovresourcesworks19077475",
      "@type": [
        "http://id.loc.gov/ontologies/bibframe/Topic",
        "http://www.loc.gov/mads/rdf/v1#Topic"
      ],
      "http://www.w3.org/2000/01/rdf-schema#label": [
        {
          "@value": "COMICS & GRAPHIC NOVELS / Nonfiction"
        }
      ],
      "http://www.loc.gov/mads/rdf/v1#authoritativeLabel": [
        {
          "@value": "COMICS & GRAPHIC NOVELS / Nonfiction"
        }
      ],
      "http://id.loc.gov/ontologies/bflc/aap-normalized": [
        {
          "@value": "comics&graphicnovels/nonfiction"
        }
      ],
      "http://www.loc.gov/mads/rdf/v1#isMemberOfMADSScheme": [
        {
          "@id": "http://id.loc.gov/vocabulary/subjectSchemes/bisacsh"
        }
      ],
      "http://id.loc.gov/ontologies/bibframe/source": [
        {
          "@id": "http://id.loc.gov/vocabulary/subjectSchemes/bisacsh"
        }
      ]
    },
    {
      "@id": "_:b487iddOtlocdOtgovresourcesworks19077475",
      "@type": [
        "http://www.loc.gov/mads/rdf/v1#Topic"
      ],
      "http://www.loc.gov/mads/rdf/v1#authoritativeLabel": [
        {
          "@value": "Refugees"
        }
      ]
    },
    {
      "@id": "_:b80iddOtlocdOtgovresourcesworks19077475",
      "@type": [
        "http://id.loc.gov/ontologies/bibframe/Classification"
      ],
      "http://id.loc.gov/ontologies/bibframe/classificationPortion": [
        {
          "@value": "BIO026000"
        }
      ],
      "http://id.loc.gov/ontologies/bibframe/source": [
        {
          "@id": "_:b84iddOtlocdOtgovresourcesworks19077475"
        }
      ]
    },
    {
      "@id": "http://id.loc.gov/rwo/agents/n2017009993",
      "@type": [
        "http://id.loc.gov/ontologies/bibframe/Agent",
        "http://id.loc.gov/ontologies/bibframe/Person",
        "http://www.loc.gov/mads/rdf/v1#PersonalName",
        "http://www.loc.gov/mads/rdf/v1#PersonalName"
      ],
      "http://www.w3.org/2000/01/rdf-schema#label": [
        {
          "@value": "Bui, Thi"
        },
        {
          "@value": "Bui, Thi"
        },
        {
          "@value": "Bui, Thi"
        }
      ],
      "http://id.loc.gov/ontologies/bflc/marcKey": [
        {
          "@value": "1001 $aBui, Thi"
        },
        {
          "@value": "1001 $aBui, Thi"
        },
        {
          "@value": "1001 $aBui, Thi"
        }
      ]
    },
    {
      "@id": "_:b217iddOtlocdOtgovresourcesworks19077475",
      "@type": [
        "http://id.loc.gov/ontologies/bibframe/Topic",
        "http://www.loc.gov/mads/rdf/v1#ComplexSubject"
      ],
      "http://www.w3.org/2000/01/rdf-schema#label": [
        {
          "@value": "Refugees--United States--Biography--Comic books, strips, etc."
        }
      ],
      "http://www.loc.gov/mads/rdf/v1#authoritativeLabel": [
        {
          "@value": "Refugees--United States--Biography--Comic books, strips, etc."
        }
      ],
      "http://www.loc.gov/mads/rdf/v1#isMemberOfMADSScheme": [
        {
          "@id": "http://id.loc.gov/authorities/subjects"
        }
      ],
      "http://www.loc.gov/mads/rdf/v1#componentList": [
        {
          "@list": [
            {
              "@id": "http://id.loc.gov/authorities/subjects/sh85112299"
            },
            {
              "@id": "http://id.loc.gov/rwo/agents/n78095330-781"
            },
            {
              "@id": "http://id.loc.gov/authorities/subjects/sh99001237"
            },
            {
              "@id": "http://id.loc.gov/authorities/subjects/sh99001401"
            }
          ]
        }
      ],
      "http://id.loc.gov/ontologies/bflc/aap-normalized": [
        {
          "@value": "refugeesunitedstatesbiographycomicbooksstripsetc"
        }
      ],
      "http://id.loc.gov/ontologies/bibframe/source": [
        {
          "@id": "http://id.loc.gov/authorities/subjects"
        }
      ]
    },
    {
      "@id": "_:b318iddOtlocdOtgovresourcesworks19077475",
      "@type": [
        "http://www.loc.gov/mads/rdf/v1#Topic"
      ],
      "http://www.loc.gov/mads/rdf/v1#authoritativeLabel": [
        {
          "@value": "Biography"
        }
      ]
    },
    {
      "@id": "_:b390iddOtlocdOtgovresourcesworks19077475",
      "@type": [
        "http://id.loc.gov/ontologies/bibframe/Topic",
        "http://www.loc.gov/mads/rdf/v1#Topic"
      ],
      "http://www.w3.org/2000/01/rdf-schema#label": [
        {
          "@value": "SOCIAL SCIENCE / Emigration & Immigration"
        }
      ],
      "http://www.loc.gov/mads/rdf/v1#authoritativeLabel": [
        {
          "@value": "SOCIAL SCIENCE / Emigration & Immigration"
        }
      ],
      "http://id.loc.gov/ontologies/bflc/aap-normalized": [
        {
          "@value": "socialscience/emigration&immigration"
        }
      ],
      "http://www.loc.gov/mads/rdf/v1#isMemberOfMADSScheme": [
        {
          "@id": "http://id.loc.gov/vocabulary/subjectSchemes/bisacsh"
        }
      ],
      "http://id.loc.gov/ontologies/bibframe/source": [
        {
          "@id": "http://id.loc.gov/vocabulary/subjectSchemes/bisacsh"
        }
      ]
    },
    {
      "@id": "_:b520iddOtlocdOtgovresourcesworks19077475",
      "@type": [
        "http://www.loc.gov/mads/rdf/v1#Topic"
      ],
      "http://www.loc.gov/mads/rdf/v1#authoritativeLabel": [
        {
          "@value": "Vietnam War, 1961-1975"
        }
      ]
    },
    {
      "@id": "_:b451iddOtlocdOtgovresourcesworks19077475",
      "@type": [
        "http://id.loc.gov/ontologies/bibframe/Topic",
        "http://www.loc.gov/mads/rdf/v1#ComplexSubject"
      ],
      "http://www.w3.org/2000/01/rdf-schema#label": [
        {
          "@value": "Vietnamese Americans--Comic books, strips, etc."
        }
      ],
      "http://www.loc.gov/mads/rdf/v1#authoritativeLabel": [
        {
          "@value": "Vietnamese Americans--Comic books, strips, etc."
        }
      ],
      "http://www.loc.gov/mads/rdf/v1#componentList": [
        {
          "@list": [
            {
              "@id": "_:b459iddOtlocdOtgovresourcesworks19077475"
            },
            {
              "@id": "_:b462iddOtlocdOtgovresourcesworks19077475"
            }
          ]
        }
      ],
      "http://id.loc.gov/ontologies/bflc/aap-normalized": [
        {
          "@value": "vietnameseamericanscomicbooksstripsetc"
        }
      ],
      "http://www.loc.gov/mads/rdf/v1#isMemberOfMADSScheme": [
        {
          "@id": "http://id.loc.gov/vocabulary/subjectSchemes/sears"
        }
      ],
      "http://id.loc.gov/ontologies/bibframe/source": [
        {
          "@id": "http://id.loc.gov/vocabulary/subjectSchemes/sears"
        }
      ]
    },
    {
      "@id": "_:b546iddOtlocdOtgovresourcesworks19077475",
      "@type": [
        "http://id.loc.gov/ontologies/bibframe/Title"
      ],
      "http://id.loc.gov/ontologies/bibframe/mainTitle": [
        {
          "@value": "The best we could do"
        }
      ],
      "http://id.loc.gov/ontologies/bibframe/subtitle": [
        {
          "@value": "an illustrated memoir"
        }
      ],
      "http://id.loc.gov/ontologies/bflc/nonSortNum": [
        {
          "@value": "4"
        }
      ]
    },
    {
      "@id": "http://id.loc.gov/vocabulary/geographicAreas/a-vt",
      "@type": [
        "http://id.loc.gov/ontologies/bibframe/GeographicCoverage"
      ],
      "http://www.w3.org/2000/01/rdf-schema#label": [
        {
          "@language": "en",
          "@value": "Vietnam"
        }
      ],
      "http://id.loc.gov/ontologies/bibframe/code": [
        {
          "@type": "http://www.w3.org/2001/XMLSchema#string",
          "@value": "a-vt"
        }
      ]
    },
    {
      "@id": "_:b92iddOtlocdOtgovresourcesworks19077475",
      "@type": [
        "http://id.loc.gov/ontologies/bibframe/Source"
      ],
      "http://id.loc.gov/ontologies/bibframe/code": [
        {
          "@value": "bisacsh"
        }
      ]
    },
    {
      "@id": "_:b612iddOtlocdOtgovresourcesworks19077475",
      "@type": [
        "http://id.loc.gov/ontologies/bibframe/AdminMetadata"
      ],
      "http://id.loc.gov/ontologies/bibframe/descriptionLevel": [
        {
          "@id": "http://id.loc.gov/ontologies/bibframe-2-3-0/"
        }
      ],
      "http://id.loc.gov/ontologies/bflc/encodingLevel": [
        {
          "@id": "http://id.loc.gov/vocabulary/menclvl/f"
        }
      ],
      "http://id.loc.gov/ontologies/bibframe/descriptionConventions": [
        {
          "@id": "http://id.loc.gov/vocabulary/descriptionConventions/isbd"
        },
        {
          "@id": "http://id.loc.gov/vocabulary/descriptionConventions/rda"
        }
      ],
      "http://id.loc.gov/ontologies/bibframe/identifiedBy": [
        {
          "@id": "_:b627iddOtlocdOtgovresourcesworks19077475"
        }
      ],
      "http://id.loc.gov/ontologies/lclocal/d906": [
        {
          "@value": "=906     $a 7 $b cbc $c copycat $d 2 $e epcn $f 20 $g y-gencatlg"
        }
      ],
      "http://id.loc.gov/ontologies/lclocal/d925": [
        {
          "@value": "=925  0  $a acquire $b 1 shelf copy $x policy default"
        }
      ],
      "http://id.loc.gov/ontologies/lclocal/d955": [
        {
          "@value": "=955     $b rf06 2017-10-19 z-processor $i rf06 2017-10-20 to CALM"
        }
      ],
      "http://id.loc.gov/ontologies/bibframe/descriptionLanguage": [
        {
          "@id": "http://id.loc.gov/vocabulary/languages/eng"
        }
      ],
      "http://id.loc.gov/ontologies/bibframe/descriptionAuthentication": [
        {
          "@id": "http://id.loc.gov/vocabulary/marcauthen/lccopycat"
        }
      ]
    },
    {
      "@id": "http://id.loc.gov/vocabulary/subjectSchemes/bisacsh",
      "@type": [
        "http://www.loc.gov/mads/rdf/v1#Authority",
        "http://id.loc.gov/ontologies/bibframe/Source",
        "http://www.loc.gov/mads/rdf/v1#Authority",
        "http://id.loc.gov/ontologies/bibframe/Source",
        "http://www.loc.gov/mads/rdf/v1#Authority",
        "http://id.loc.gov/ontologies/bibframe/Source"
      ],
      "http://www.w3.org/2000/01/rdf-schema#label": [
        {
          "@value": "BISAC subject headings"
        },
        {
          "@value": "BISAC subject headings"
        },
        {
          "@value": "BISAC subject headings"
        },
        {
          "@value": "BISAC subject headings"
        },
        {
          "@value": "BISAC subject headings"
        },
        {
          "@value": "BISAC subject headings"
        }
      ],
      "http://id.loc.gov/ontologies/bibframe/code": [
        {
          "@value": "bisacsh"
        },
        {
          "@value": "bisacsh"
        },
        {
          "@value": "bisacsh"
        },
        {
          "@value": "bisacsh"
        },
        {
          "@value": "bisacsh"
        },
        {
          "@value": "bisacsh"
        }
      ]
    },
    {
      "@id": "_:b315iddOtlocdOtgovresourcesworks19077475",
      "@type": [
        "http://www.loc.gov/mads/rdf/v1#Topic"
      ],
      "http://www.loc.gov/mads/rdf/v1#authoritativeLabel": [
        {
          "@value": "Refugees"
        }
      ]
    },
    {
      "@id": "_:b307iddOtlocdOtgovresourcesworks19077475",
      "@type": [
        "http://id.loc.gov/ontologies/bibframe/Topic",
        "http://www.loc.gov/mads/rdf/v1#ComplexSubject"
      ],
      "http://www.w3.org/2000/01/rdf-schema#label": [
        {
          "@value": "Refugees--Biography"
        }
      ],
      "http://www.loc.gov/mads/rdf/v1#authoritativeLabel": [
        {
          "@value": "Refugees--Biography"
        }
      ],
      "http://www.loc.gov/mads/rdf/v1#componentList": [
        {
          "@list": [
            {
              "@id": "_:b315iddOtlocdOtgovresourcesworks19077475"
            },
            {
              "@id": "_:b318iddOtlocdOtgovresourcesworks19077475"
            }
          ]
        }
      ],
      "http://id.loc.gov/ontologies/bflc/aap-normalized": [
        {
          "@value": "refugeesbiography"
        }
      ]
    },
    {
      "@id": "_:b462iddOtlocdOtgovresourcesworks19077475",
      "@type": [
        "http://www.loc.gov/mads/rdf/v1#GenreForm"
      ],
      "http://www.loc.gov/mads/rdf/v1#authoritativeLabel": [
        {
          "@value": "Comic books, strips, etc."
        }
      ]
    },
    {
      "@id": "_:b158iddOtlocdOtgovresourcesworks19077475",
      "@type": [
        "http://id.loc.gov/ontologies/bibframe/Topic",
        "http://www.loc.gov/mads/rdf/v1#ComplexSubject"
      ],
      "http://www.loc.gov/mads/rdf/v1#authoritativeLabel": [
        {
          "@value": "Bui, Thi--Comic books, strips, etc."
        }
      ],
      "http://www.loc.gov/mads/rdf/v1#isMemberOfMADSScheme": [
        {
          "@id": "http://id.loc.gov/authorities/subjects"
        }
      ],
      "http://www.loc.gov/mads/rdf/v1#componentList": [
        {
          "@list": [
            {
              "@id": "http://id.loc.gov/rwo/agents/n2017009993"
            },
            {
              "@id": "http://id.loc.gov/authorities/subjects/sh99001401"
            }
          ]
        }
      ],
      "http://id.loc.gov/ontologies/bflc/aap-normalized": [
        {
          "@value": "buithicomicbooksstripsetc"
        }
      ],
      "http://id.loc.gov/ontologies/bibframe/source": [
        {
          "@id": "http://id.loc.gov/authorities/subjects"
        }
      ]
    },
    {
      "@id": "http://id.loc.gov/vocabulary/subjectSchemes/sears",
      "@type": [
        "http://www.loc.gov/mads/rdf/v1#Authority",
        "http://id.loc.gov/ontologies/bibframe/Source",
        "http://www.loc.gov/mads/rdf/v1#Authority",
        "http://id.loc.gov/ontologies/bibframe/Source",
        "http://www.loc.gov/mads/rdf/v1#Authority",
        "http://id.loc.gov/ontologies/bibframe/Source",
        "http://www.loc.gov/mads/rdf/v1#Authority",
        "http://id.loc.gov/ontologies/bibframe/Source"
      ],
      "http://www.w3.org/2000/01/rdf-schema#label": [
        {
          "@value": "Sears list of subject headings"
        },
        {
          "@value": "Sears list of subject headings"
        },
        {
          "@value": "Sears list of subject headings"
        },
        {
          "@value": "Sears list of subject headings"
        },
        {
          "@value": "Sears list of subject headings"
        },
        {
          "@value": "Sears list of subject headings"
        },
        {
          "@value": "Sears list of subject headings"
        },
        {
          "@value": "Sears list of subject headings"
        }
      ],
      "http://id.loc.gov/ontologies/bibframe/code": [
        {
          "@value": "sears"
        },
        {
          "@value": "sears"
        },
        {
          "@value": "sears"
        },
        {
          "@value": "sears"
        },
        {
          "@value": "sears"
        },
        {
          "@value": "sears"
        },
        {
          "@value": "sears"
        },
        {
          "@value": "sears"
        }
      ]
    },
    {
      "@id": "_:b479iddOtlocdOtgovresourcesworks19077475",
      "@type": [
        "http://id.loc.gov/ontologies/bibframe/Topic",
        "http://www.loc.gov/mads/rdf/v1#ComplexSubject"
      ],
      "http://www.w3.org/2000/01/rdf-schema#label": [
        {
          "@value": "Refugees--United States--Comic books, strips, etc."
        }
      ],
      "http://www.loc.gov/mads/rdf/v1#authoritativeLabel": [
        {
          "@value": "Refugees--United States--Comic books, strips, etc."
        }
      ],
      "http://www.loc.gov/mads/rdf/v1#componentList": [
        {
          "@list": [
            {
              "@id": "_:b487iddOtlocdOtgovresourcesworks19077475"
            },
            {
              "@id": "http://id.loc.gov/rwo/agents/n78095330-781"
            },
            {
              "@id": "_:b495iddOtlocdOtgovresourcesworks19077475"
            }
          ]
        }
      ],
      "http://id.loc.gov/ontologies/bflc/aap-normalized": [
        {
          "@value": "refugeesunitedstatescomicbooksstripsetc"
        }
      ],
      "http://www.loc.gov/mads/rdf/v1#isMemberOfMADSScheme": [
        {
          "@id": "http://id.loc.gov/vocabulary/subjectSchemes/sears"
        }
      ],
      "http://id.loc.gov/ontologies/bibframe/source": [
        {
          "@id": "http://id.loc.gov/vocabulary/subjectSchemes/sears"
        }
      ]
    }
  ],
  "instance": [
    {
      "@id": "_:b43iddOtlocdOtgovresourcesinstances19077475",
      "@type": [
        "http://id.loc.gov/ontologies/bibframe/OclcNumber"
      ],
      "http://www.w3.org/1999/02/22-rdf-syntax-ns#value": [
        {
          "@value": "ocn947796066"
        }
      ]
    },
    {
      "@id": "_:b127iddOtlocdOtgovresourcesinstances19077475",
      "@type": [
        "http://id.loc.gov/ontologies/bibframe/AdminMetadata"
      ],
      "http://id.loc.gov/ontologies/bibframe/status": [
        {
          "@id": "http://id.loc.gov/vocabulary/mstatus/c"
        }
      ],
      "http://id.loc.gov/ontologies/bibframe/date": [
        {
          "@type": "http://www.w3.org/2001/XMLSchema#dateTime",
          "@value": "2017-10-26T08:31:24"
        }
      ],
      "http://id.loc.gov/ontologies/bibframe/descriptionModifier": [
        {
          "@id": "http://id.loc.gov/vocabulary/organizations/dlc"
        }
      ]
    },
    {
      "@id": "_:b147iddOtlocdOtgovresourcesinstances19077475",
      "@type": [
        "http://id.loc.gov/ontologies/bibframe/AdminMetadata"
      ],
      "http://id.loc.gov/ontologies/bibframe/status": [
        {
          "@id": "http://id.loc.gov/vocabulary/mstatus/c"
        }
      ],
      "http://id.loc.gov/ontologies/bibframe/agent": [
        {
          "@id": "http://id.loc.gov/vocabulary/organizations/dlcmrc"
        }
      ],
      "http://id.loc.gov/ontologies/bibframe/generationProcess": [
        {
          "@id": "https://github.com/lcnetdev/marc2bibframe2/releases/tag/v2.7.0"
        }
      ],
      "http://id.loc.gov/ontologies/bibframe/date": [
        {
          "@type": "http://www.w3.org/2001/XMLSchema#dateTime",
          "@value": "2024-08-03T16:20:01.711247-04:00"
        }
      ]
    },
    {
      "@id": "_:b85iddOtlocdOtgovresourcesinstances19077475",
      "@type": [
        "http://id.loc.gov/ontologies/bibframe/Contribution",
        "http://id.loc.gov/ontologies/bibframe/PrimaryContribution"
      ],
      "http://id.loc.gov/ontologies/bibframe/agent": [
        {
          "@id": "http://id.loc.gov/rwo/agents/n2017009993"
        }
      ],
      "http://id.loc.gov/ontologies/bibframe/role": [
        {
          "@id": "http://id.loc.gov/vocabulary/relators/aut"
        },
        {
          "@id": "http://id.loc.gov/vocabulary/relators/art"
        }
      ]
    },
    {
      "@id": "_:b31iddOtlocdOtgovresourcesinstances19077475",
      "@type": [
        "http://id.loc.gov/ontologies/bibframe/Lccn"
      ],
      "http://www.w3.org/1999/02/22-rdf-syntax-ns#value": [
        {
          "@value": "  2016940170"
        }
      ]
    },
    {
      "@id": "http://id.loc.gov/vocabulary/relators/aut",
      "@type": [
        "http://id.loc.gov/ontologies/bibframe/Role"
      ],
      "http://www.w3.org/2000/01/rdf-schema#label": [
        {
          "@value": "Author"
        }
      ],
      "http://id.loc.gov/ontologies/bibframe/code": [
        {
          "@value": "aut"
        }
      ]
    },
    {
      "@id": "_:b123iddOtlocdOtgovresourcesinstances19077475",
      "@type": [
        "http://id.loc.gov/ontologies/bibframe/Agent"
      ],
      "http://id.loc.gov/ontologies/bibframe/code": [
        {
          "@value": "BTCTA"
        }
      ]
    },
    {
      "@id": "http://id.loc.gov/vocabulary/countries/nyu",
      "@type": [
        "http://id.loc.gov/ontologies/bibframe/Place"
      ],
      "http://www.w3.org/2000/01/rdf-schema#label": [
        {
          "@language": "en",
          "@value": "New York (State)"
        }
      ],
      "http://id.loc.gov/ontologies/bibframe/code": [
        {
          "@type": "http://www.w3.org/2001/XMLSchema#string",
          "@value": "nyu"
        }
      ]
    },
    {
      "@id": "_:b35iddOtlocdOtgovresourcesinstances19077475",
      "@type": [
        "http://id.loc.gov/ontologies/bibframe/Isbn"
      ],
      "http://www.w3.org/1999/02/22-rdf-syntax-ns#value": [
        {
          "@value": "9781419718779"
        }
      ]
    },
    {
      "@id": "_:b39iddOtlocdOtgovresourcesinstances19077475",
      "@type": [
        "http://id.loc.gov/ontologies/bibframe/Isbn"
      ],
      "http://www.w3.org/1999/02/22-rdf-syntax-ns#value": [
        {
          "@value": "1419718770"
        }
      ]
    },
    {
      "@id": "http://id.loc.gov/vocabulary/descriptionConventions/rda",
      "@type": [
        "http://id.loc.gov/ontologies/bibframe/DescriptionConventions"
      ],
      "http://www.w3.org/2000/01/rdf-schema#label": [
        {
          "@value": "Resource description and access"
        }
      ],
      "http://id.loc.gov/ontologies/bibframe/code": [
        {
          "@value": "rda"
        }
      ]
    },
    {
      "@id": "http://id.loc.gov/vocabulary/organizations/dlc",
      "@type": [
        "http://id.loc.gov/ontologies/bibframe/Organization",
        "http://id.loc.gov/ontologies/bibframe/Organization"
      ],
      "http://www.w3.org/2000/01/rdf-schema#label": [
        {
          "@value": "United States, Library of Congress"
        },
        {
          "@value": "United States, Library of Congress"
        }
      ],
      "http://id.loc.gov/ontologies/bibframe/code": [
        {
          "@type": "http://id.loc.gov/datatypes/orgs/code",
          "@value": "DLC"
        },
        {
          "@type": "http://id.loc.gov/datatypes/orgs/normalized",
          "@value": "dlc"
        },
        {
          "@type": "http://id.loc.gov/datatypes/orgs/iso15511",
          "@value": "US-dlc"
        },
        {
          "@type": "http://id.loc.gov/datatypes/orgs/code",
          "@value": "DLC"
        },
        {
          "@type": "http://id.loc.gov/datatypes/orgs/normalized",
          "@value": "dlc"
        },
        {
          "@type": "http://id.loc.gov/datatypes/orgs/iso15511",
          "@value": "US-dlc"
        }
      ]
    },
    {
      "@id": "http://id.loc.gov/vocabulary/marcauthen/lccopycat",
      "@type": [
        "http://id.loc.gov/ontologies/bibframe/DescriptionAuthentication"
      ],
      "http://www.w3.org/2000/01/rdf-schema#label": [
        {
          "@value": "LC Copy Cataloging"
        }
      ],
      "http://id.loc.gov/ontologies/bibframe/code": [
        {
          "@value": "lccopycat"
        }
      ]
    },
    {
      "@id": "_:b57iddOtlocdOtgovresourcesinstances19077475",
      "@type": [
        "http://id.loc.gov/ontologies/bibframe/Extent"
      ],
      "http://www.w3.org/2000/01/rdf-schema#label": [
        {
          "@value": "327 pages"
        }
      ]
    },
    {
      "@id": "_:b61iddOtlocdOtgovresourcesinstances19077475",
      "@type": [
        "http://id.loc.gov/ontologies/bibframe/Note",
        "http://id.loc.gov/vocabulary/mnotetype/physical"
      ],
      "http://www.w3.org/2000/01/rdf-schema#label": [
        {
          "@value": "illustrations (chiefly color)"
        }
      ]
    },
    {
      "@id": "http://id.loc.gov/vocabulary/menclvl/f",
      "@type": [
        "http://id.loc.gov/ontologies/bflc/EncodingLevel"
      ],
      "http://www.w3.org/2000/01/rdf-schema#label": [
        {
          "@value": "full"
        }
      ],
      "http://id.loc.gov/ontologies/bibframe/code": [
        {
          "@value": "f"
        }
      ]
    },
    {
      "@id": "http://id.loc.gov/vocabulary/mediaTypes/n",
      "@type": [
        "http://id.loc.gov/ontologies/bibframe/Media"
      ],
      "http://www.w3.org/2000/01/rdf-schema#label": [
        {
          "@value": "unmediated"
        }
      ],
      "http://id.loc.gov/ontologies/bibframe/code": [
        {
          "@value": "n"
        }
      ]
    },
    {
      "@id": "http://id.loc.gov/vocabulary/descriptionConventions/isbd",
      "@type": [
        "http://id.loc.gov/ontologies/bibframe/DescriptionConventions"
      ],
      "http://www.w3.org/2000/01/rdf-schema#label": [
        {
          "@value": "ISBD: International standard bibliographic description"
        }
      ],
      "http://id.loc.gov/ontologies/bibframe/code": [
        {
          "@value": "isbd"
        }
      ]
    },
    {
      "@id": "http://id.loc.gov/vocabulary/languages/eng",
      "@type": [
        "http://id.loc.gov/ontologies/bibframe/Language"
      ],
      "http://www.w3.org/2000/01/rdf-schema#label": [
        {
          "@language": "en",
          "@value": "English"
        }
      ],
      "http://id.loc.gov/ontologies/bibframe/code": [
        {
          "@type": "http://www.w3.org/2001/XMLSchema#string",
          "@value": "eng"
        }
      ]
    },
    {
      "@id": "http://id.loc.gov/resources/instances/19077475",
      "@type": [
        "http://id.loc.gov/ontologies/bibframe/Instance"
      ],
      "http://id.loc.gov/ontologies/bibframe/issuance": [
        {
          "@id": "http://id.loc.gov/vocabulary/issuance/mono"
        }
      ],
      "http://id.loc.gov/ontologies/bibframe/provisionActivity": [
        {
          "@id": "_:b10iddOtlocdOtgovresourcesinstances19077475"
        }
      ],
      "http://id.loc.gov/ontologies/bibframe/publicationStatement": [
        {
          "@value": "New York: Abrams ComicArts, 2017"
        }
      ],
      "http://id.loc.gov/ontologies/bibframe/copyrightDate": [
        {
          "@type": "http://id.loc.gov/datatypes/edtf",
          "@value": "2017"
        }
      ],
      "http://id.loc.gov/ontologies/bibframe/identifiedBy": [
        {
          "@id": "_:b31iddOtlocdOtgovresourcesinstances19077475"
        },
        {
          "@id": "_:b35iddOtlocdOtgovresourcesinstances19077475"
        },
        {
          "@id": "_:b39iddOtlocdOtgovresourcesinstances19077475"
        },
        {
          "@id": "_:b43iddOtlocdOtgovresourcesinstances19077475"
        }
      ],
      "http://id.loc.gov/ontologies/bibframe/responsibilityStatement": [
        {
          "@value": "Thi Bui"
        }
      ],
      "http://id.loc.gov/ontologies/bibframe/title": [
        {
          "@id": "_:b49iddOtlocdOtgovresourcesinstances19077475"
        }
      ],
      "http://id.loc.gov/ontologies/bibframe/extent": [
        {
          "@id": "_:b57iddOtlocdOtgovresourcesinstances19077475"
        }
      ],
      "http://id.loc.gov/ontologies/bibframe/note": [
        {
          "@id": "_:b61iddOtlocdOtgovresourcesinstances19077475"
        }
      ],
      "http://id.loc.gov/ontologies/bibframe/dimensions": [
        {
          "@value": "24 cm"
        }
      ],
      "http://id.loc.gov/ontologies/bibframe/media": [
        {
          "@id": "http://id.loc.gov/vocabulary/mediaTypes/n"
        }
      ],
      "http://id.loc.gov/ontologies/bibframe/carrier": [
        {
          "@id": "http://id.loc.gov/vocabulary/carriers/nc"
        }
      ],
      "http://purl.org/dc/terms/isPartOf": [
        {
          "@id": "http://id.loc.gov/resources/instances"
        }
      ],
      "http://id.loc.gov/ontologies/bibframe/instanceOf": [
        {
          "@id": "http://id.loc.gov/resources/works/19077475"
        }
      ],
      "http://id.loc.gov/ontologies/bibframe/adminMetadata": [
        {
          "@id": "_:b113iddOtlocdOtgovresourcesinstances19077475"
        },
        {
          "@id": "_:b127iddOtlocdOtgovresourcesinstances19077475"
        },
        {
          "@id": "_:b147iddOtlocdOtgovresourcesinstances19077475"
        },
        {
          "@id": "_:b169iddOtlocdOtgovresourcesinstances19077475"
        }
      ]
    },
    {
      "@id": "http://id.loc.gov/rwo/agents/n2017009993",
      "@type": [
        "http://id.loc.gov/ontologies/bibframe/Agent",
        "http://id.loc.gov/ontologies/bibframe/Person"
      ],
      "http://www.w3.org/2000/01/rdf-schema#label": [
        {
          "@value": "Bui, Thi"
        }
      ],
      "http://id.loc.gov/ontologies/bflc/marcKey": [
        {
          "@value": "1001 $aBui, Thi"
        }
      ]
    },
    {
      "@id": "_:b113iddOtlocdOtgovresourcesinstances19077475",
      "@type": [
        "http://id.loc.gov/ontologies/bibframe/AdminMetadata"
      ],
      "http://id.loc.gov/ontologies/bibframe/status": [
        {
          "@id": "http://id.loc.gov/vocabulary/mstatus/n"
        }
      ],
      "http://id.loc.gov/ontologies/bibframe/date": [
        {
          "@type": "http://www.w3.org/2001/XMLSchema#date",
          "@value": "2016-04-28"
        }
      ],
      "http://id.loc.gov/ontologies/bibframe/agent": [
        {
          "@id": "_:b123iddOtlocdOtgovresourcesinstances19077475"
        }
      ]
    },
    {
      "@id": "http://id.loc.gov/vocabulary/organizations/dlcmrc",
      "@type": [
        "http://id.loc.gov/ontologies/bibframe/Agent",
        "http://id.loc.gov/ontologies/bibframe/Organization"
      ],
      "http://www.w3.org/2000/01/rdf-schema#label": [
        {
          "@value": "United States, Library of Congress, Network Development and MARC Standards Office"
        }
      ],
      "http://id.loc.gov/ontologies/bibframe/code": [
        {
          "@type": "http://id.loc.gov/datatypes/orgs/code",
          "@value": "DLC-MRC"
        },
        {
          "@type": "http://id.loc.gov/datatypes/orgs/normalized",
          "@value": "dlcmrc"
        },
        {
          "@type": "http://id.loc.gov/datatypes/orgs/iso15511",
          "@value": "US-dlcmrc"
        }
      ]
    },
    {
      "@id": "http://id.loc.gov/vocabulary/carriers/nc",
      "@type": [
        "http://id.loc.gov/ontologies/bibframe/Carrier"
      ],
      "http://www.w3.org/2000/01/rdf-schema#label": [
        {
          "@value": "volume"
        }
      ],
      "http://id.loc.gov/ontologies/bibframe/code": [
        {
          "@value": "nc"
        }
      ]
    },
    {
      "@id": "_:b10iddOtlocdOtgovresourcesinstances19077475",
      "@type": [
        "http://id.loc.gov/ontologies/bibframe/ProvisionActivity",
        "http://id.loc.gov/ontologies/bibframe/Publication"
      ],
      "http://id.loc.gov/ontologies/bibframe/date": [
        {
          "@type": "http://id.loc.gov/datatypes/edtf",
          "@value": "2017"
        }
      ],
      "http://id.loc.gov/ontologies/bibframe/place": [
        {
          "@id": "http://id.loc.gov/vocabulary/countries/nyu"
        }
      ],
      "http://id.loc.gov/ontologies/bflc/simplePlace": [
        {
          "@value": "New York"
        }
      ],
      "http://id.loc.gov/ontologies/bflc/simpleAgent": [
        {
          "@value": "Abrams ComicArts"
        }
      ],
      "http://id.loc.gov/ontologies/bflc/simpleDate": [
        {
          "@value": "2017"
        }
      ]
    },
    {
      "@id": "_:b49iddOtlocdOtgovresourcesinstances19077475",
      "@type": [
        "http://id.loc.gov/ontologies/bibframe/Title"
      ],
      "http://id.loc.gov/ontologies/bibframe/mainTitle": [
        {
          "@value": "The best we could do"
        }
      ],
      "http://id.loc.gov/ontologies/bibframe/subtitle": [
        {
          "@value": "an illustrated memoir"
        }
      ],
      "http://id.loc.gov/ontologies/bflc/nonSortNum": [
        {
          "@value": "4"
        }
      ]
    },
    {
      "@id": "_:b169iddOtlocdOtgovresourcesinstances19077475",
      "@type": [
        "http://id.loc.gov/ontologies/bibframe/AdminMetadata"
      ],
      "http://id.loc.gov/ontologies/bibframe/descriptionLevel": [
        {
          "@id": "http://id.loc.gov/ontologies/bibframe-2-3-0/"
        }
      ],
      "http://id.loc.gov/ontologies/bflc/encodingLevel": [
        {
          "@id": "http://id.loc.gov/vocabulary/menclvl/f"
        }
      ],
      "http://id.loc.gov/ontologies/bibframe/descriptionConventions": [
        {
          "@id": "http://id.loc.gov/vocabulary/descriptionConventions/isbd"
        },
        {
          "@id": "http://id.loc.gov/vocabulary/descriptionConventions/rda"
        }
      ],
      "http://id.loc.gov/ontologies/bibframe/identifiedBy": [
        {
          "@id": "_:b184iddOtlocdOtgovresourcesinstances19077475"
        }
      ],
      "http://id.loc.gov/ontologies/lclocal/d906": [
        {
          "@value": "=906     $a 7 $b cbc $c copycat $d 2 $e epcn $f 20 $g y-gencatlg"
        }
      ],
      "http://id.loc.gov/ontologies/lclocal/d925": [
        {
          "@value": "=925  0  $a acquire $b 1 shelf copy $x policy default"
        }
      ],
      "http://id.loc.gov/ontologies/lclocal/d955": [
        {
          "@value": "=955     $b rf06 2017-10-19 z-processor $i rf06 2017-10-20 to CALM"
        }
      ],
      "http://id.loc.gov/ontologies/bibframe/descriptionLanguage": [
        {
          "@id": "http://id.loc.gov/vocabulary/languages/eng"
        }
      ],
      "http://id.loc.gov/ontologies/bibframe/descriptionAuthentication": [
        {
          "@id": "http://id.loc.gov/vocabulary/marcauthen/lccopycat"
        }
      ]
    },
    {
      "@id": "_:b107iddOtlocdOtgovresourcesinstances19077475",
      "@type": [
        "http://id.loc.gov/ontologies/bibframe/Title"
      ],
      "http://id.loc.gov/ontologies/bibframe/mainTitle": [
        {
          "@value": "The best we could do"
        }
      ],
      "http://id.loc.gov/ontologies/bflc/nonSortNum": [
        {
          "@value": "4"
        }
      ]
    },
    {
      "@id": "http://id.loc.gov/vocabulary/issuance/mono",
      "@type": [
        "http://id.loc.gov/ontologies/bibframe/Issuance"
      ],
      "http://www.w3.org/2000/01/rdf-schema#label": [
        {
          "@value": "single unit"
        }
      ],
      "http://id.loc.gov/ontologies/bibframe/code": [
        {
          "@value": "mono"
        }
      ]
    },
    {
      "@id": "http://id.loc.gov/vocabulary/mstatus/c",
      "@type": [
        "http://id.loc.gov/ontologies/bibframe/Status",
        "http://id.loc.gov/ontologies/bibframe/Status"
      ],
      "http://www.w3.org/2000/01/rdf-schema#label": [
        {
          "@value": "changed"
        },
        {
          "@value": "changed"
        }
      ],
      "http://id.loc.gov/ontologies/bibframe/code": [
        {
          "@value": "c"
        },
        {
          "@value": "c"
        }
      ]
    },
    {
      "@id": "_:b184iddOtlocdOtgovresourcesinstances19077475",
      "@type": [
        "http://id.loc.gov/ontologies/bibframe/Local"
      ],
      "http://www.w3.org/1999/02/22-rdf-syntax-ns#value": [
        {
          "@value": "19077475"
        }
      ],
      "http://id.loc.gov/ontologies/bibframe/assigner": [
        {
          "@id": "http://id.loc.gov/vocabulary/organizations/dlc"
        }
      ]
    },
    {
      "@id": "http://id.loc.gov/vocabulary/relators/art",
      "@type": [
        "http://id.loc.gov/ontologies/bibframe/Role"
      ],
      "http://www.w3.org/2000/01/rdf-schema#label": [
        {
          "@value": "Artist"
        }
      ],
      "http://id.loc.gov/ontologies/bibframe/code": [
        {
          "@value": "art"
        }
      ]
    },
    {
      "@id": "http://id.loc.gov/resources/works/19077475",
      "@type": [
        "http://id.loc.gov/ontologies/bibframe/Work"
      ],
      "http://www.w3.org/2000/01/rdf-schema#label": [
        {
          "@value": "Bui, Thi The best we could do"
        }
      ],
      "http://id.loc.gov/ontologies/bibframe/contribution": [
        {
          "@id": "_:b85iddOtlocdOtgovresourcesinstances19077475"
        }
      ],
      "http://id.loc.gov/ontologies/bibframe/title": [
        {
          "@id": "_:b107iddOtlocdOtgovresourcesinstances19077475"
        }
      ]
    },
    {
      "@id": "http://id.loc.gov/vocabulary/mstatus/n",
      "@type": [
        "http://id.loc.gov/ontologies/bibframe/Status"
      ],
      "http://www.w3.org/2000/01/rdf-schema#label": [
        {
          "@value": "new"
        }
      ],
      "http://id.loc.gov/ontologies/bibframe/code": [
        {
          "@value": "n"
        }
      ]
    }
  ]
}